cli2web/__init__.py
cli2web/__main__.py
cli2web/cli_parser.py
cli2web/process_manager.py
cli2web/web_generator.py
cli2web/web_server.py
cli2web/templates/base.html
cli2web/templates/cli_form.html
cli2webui-0.2.1.dist-info/METADATA
cli2webui-0.2.1.dist-info/WHEEL
cli2webui-0.2.1.dist-info/entry_points.txt
cli2webui-0.2.1.dist-info/top_level.txt
cli2webui-0.2.1.dist-info/RECORD
