Metadata-Version: 2.1
Name: cli2webui
Version: 0.2.1
Summary: A tool to convert CLI tools to web interfaces
Home-page: https://github.com/wangmaobin/cli2webui
Author: Wang Maobin
Author-email: skyfire <skyfireitdiy@hotmail.com>
License: MIT
Project-URL: Homepage, https://github.com/skyfireitdiy/cli2web
Project-URL: Repository, https://github.com/skyfireitdiy/cli2web.git
Classifier: Development Status :: 4 - Beta
Classifier: Intended Audience :: Developers
Classifier: License :: OSI Approved :: MIT License
Classifier: Programming Language :: Python :: 3
Classifier: Programming Language :: Python :: 3.8
Classifier: Programming Language :: Python :: 3.9
Classifier: Programming Language :: Python :: 3.10
Requires-Python: >=3.6
Requires-Dist: Flask>=2.0.0
Requires-Dist: Flask-SocketIO>=5.0.0
Requires-Dist: eventlet>=0.33.0
Requires-Dist: python-socketio>=5.0.0
Requires-Dist: python-engineio>=4.0.0
Requires-Dist: urllib3<2.0.0,>=1.26.0
Requires-Dist: pygments<3.0.0,>=2.13.0
Requires-Dist: tqdm>=4.64.1
